linkcheck/__init__.py
linkcheck/__main__.py
linkcheck/_release.py
linkcheck/ansicolor.py
linkcheck/better_exchook2.py
linkcheck/cmdline.py
linkcheck/colorama.py
linkcheck/containers.py
linkcheck/cookies.py
linkcheck/decorators.py
linkcheck/dummy.py
linkcheck/fileutil.py
linkcheck/ftpparse.py
linkcheck/httputil.py
linkcheck/i18n.py
linkcheck/lc_cgi.py
linkcheck/loader.py
linkcheck/lock.py
linkcheck/log.py
linkcheck/logconf.py
linkcheck/memoryutil.py
linkcheck/mimeutil.py
linkcheck/robotparser2.py
linkcheck/socketutil.py
linkcheck/strformat.py
linkcheck/threader.py
linkcheck/trace.py
linkcheck/url.py
linkcheck/bookmarks/__init__.py
linkcheck/bookmarks/chromium.py
linkcheck/bookmarks/firefox.py
linkcheck/bookmarks/opera.py
linkcheck/bookmarks/safari.py
linkcheck/cache/__init__.py
linkcheck/cache/results.py
linkcheck/cache/robots_txt.py
linkcheck/cache/urlqueue.py
linkcheck/checker/__init__.py
linkcheck/checker/const.py
linkcheck/checker/dnsurl.py
linkcheck/checker/fileurl.py
linkcheck/checker/ftpurl.py
linkcheck/checker/httpurl.py
linkcheck/checker/ignoreurl.py
linkcheck/checker/internpaturl.py
linkcheck/checker/itmsservicesurl.py
linkcheck/checker/mailtourl.py
linkcheck/checker/unknownurl.py
linkcheck/checker/urlbase.py
linkcheck/command/__init__.py
linkcheck/command/arg_parser.py
linkcheck/command/linkchecker.py
linkcheck/command/setup_config.py
linkcheck/configuration/__init__.py
linkcheck/configuration/confparse.py
linkcheck/data/__init__.py
linkcheck/data/linkcheckerrc
linkcheck/data/locale/de/LC_MESSAGES/linkchecker.mo
linkcheck/data/locale/es/LC_MESSAGES/linkchecker.mo
linkcheck/data/locale/fr/LC_MESSAGES/linkchecker.mo
linkcheck/data/locale/nl_NL/LC_MESSAGES/linkchecker.mo
linkcheck/director/__init__.py
linkcheck/director/aggregator.py
linkcheck/director/checker.py
linkcheck/director/console.py
linkcheck/director/interrupter.py
linkcheck/director/logger.py
linkcheck/director/status.py
linkcheck/director/task.py
linkcheck/htmlutil/__init__.py
LinkChecker-10.5.0.dist-info/METADATA
LinkChecker-10.5.0.dist-info/WHEEL
LinkChecker-10.5.0.dist-info/entry_points.txt
LinkChecker-10.5.0.dist-info/licenses/COPYING
LinkChecker-10.5.0.dist-info/RECORD
